li-test/__init__.py
li-test/test.py
litest/__init__.py
litest/test.py
li_robot_parameter_change_monitor_source-0.2.1.dist-info/METADATA
li_robot_parameter_change_monitor_source-0.2.1.dist-info/WHEEL
li_robot_parameter_change_monitor_source-0.2.1.dist-info/top_level.txt
li_robot_parameter_change_monitor_source-0.2.1.dist-info/RECORD
